.class public test34
.super java/lang/Object

.method public static main([Ljava/lang/String;)V
	.limit stack 50
	.limit locals 6
;  (29) Method Declaration (main)
;  (30) Local Variable Declaration
;  (30) NewArray
;  (30) ArrayLiteral
	iconst_4
	anewarray [LA;
	dup
	iconst_0
;  (30) ArrayLiteral
	iconst_2
	anewarray A
	dup
	iconst_0
;  (30) New
	new A
	dup
;  (30) Literal
	ldc "Hello"
;  (30) End Literal
	invokespecial A/<init>(Ljava/lang/String;)V
;  (30) End New
	aastore
	dup
	iconst_1
;  (30) New
	new A
	dup
;  (30) Literal
	ldc "World"
;  (30) End Literal
	invokespecial A/<init>(Ljava/lang/String;)V
;  (30) End New
	aastore
;  (30) End ArrayLiteral
	aastore
	dup
	iconst_1
;  (31) ArrayLiteral
	iconst_2
	anewarray A
	dup
	iconst_0
;  (31) New
	new A
	dup
;  (31) Literal
	ldc "Hej"
;  (31) End Literal
	invokespecial A/<init>(Ljava/lang/String;)V
;  (31) End New
	aastore
	dup
	iconst_1
;  (31) New
	new A
	dup
;  (31) Literal
	ldc "Verden"
;  (31) End Literal
	invokespecial A/<init>(Ljava/lang/String;)V
;  (31) End New
	aastore
;  (31) End ArrayLiteral
	aastore
	dup
	iconst_2
;  (32) ArrayLiteral
	iconst_2
	anewarray A
	dup
	iconst_0
;  (32) New
	new A
	dup
;  (32) Literal
	ldc "Hallo"
;  (32) End Literal
	invokespecial A/<init>(Ljava/lang/String;)V
;  (32) End New
	aastore
	dup
	iconst_1
;  (32) New
	new A
	dup
;  (32) Literal
	ldc "Welt"
;  (32) End Literal
	invokespecial A/<init>(Ljava/lang/String;)V
;  (32) End New
	aastore
;  (32) End ArrayLiteral
	aastore
	dup
	iconst_3
;  (33) ArrayLiteral
	iconst_2
	anewarray A
	dup
	iconst_0
;  (33) New
	new A
	dup
;  (33) Literal
	ldc "Hola"
;  (33) End Literal
	invokespecial A/<init>(Ljava/lang/String;)V
;  (33) End New
	aastore
	dup
	iconst_1
;  (33) New
	new A
	dup
;  (33) Literal
	ldc "Mundo"
;  (33) End Literal
	invokespecial A/<init>(Ljava/lang/String;)V
;  (33) End New
	aastore
;  (33) End ArrayLiteral
	aastore
;  (30) End ArrayLiteral
;  (30) End NewArray
	astore_1
;  (30) End LocalDecl
;  (34) For Statement
;  (34) Local Variable Declaration
;  (34) Literal
	iconst_0
;  (34) End Literal
	istore_2
;  (34) End LocalDecl
L1:
;  (34) Binary Expression
;  (34) Name Expression --
	iload_2
;  (34) End NameExpr
;  (34) Array length
;  (34) Name Expression --
	aload_1
;  (34) End NameExpr
	arraylength
	if_icmplt L4
	iconst_0
	goto L5
L4:
	iconst_1
L5:
;  (34) End BinaryExpr
	ifeq L2
;  (35) For Statement
;  (35) Local Variable Declaration
;  (35) Literal
	iconst_0
;  (35) End Literal
	istore_3
;  (35) End LocalDecl
L6:
;  (35) Binary Expression
;  (35) Name Expression --
	iload_3
;  (35) End NameExpr
;  (35) Array length
;  (35) ArrayAccessExpr
;  (35) Name Expression --
	aload_1
;  (35) End NameExpr
;  (35) Name Expression --
	iload_2
;  (35) End NameExpr
	aaload
;  (35) End ArrayAccessExpr
	arraylength
	if_icmplt L9
	iconst_0
	goto L10
L9:
	iconst_1
L10:
;  (35) End BinaryExpr
	ifeq L7
;  (36) Expression Statement
;  (36) Invocation
;  (36) ArrayAccessExpr
;  (36) ArrayAccessExpr
;  (36) Name Expression --
	aload_1
;  (36) End NameExpr
;  (36) Name Expression --
	iload_2
;  (36) End NameExpr
	aaload
;  (36) End ArrayAccessExpr
;  (36) Name Expression --
	iload_3
;  (36) End NameExpr
	aaload
;  (36) End ArrayAccessExpr
	invokevirtual A/print()V
;  (36) End Invocation
;  (36) End ExprStat
L8:
;  (35) Expression Statement
;  (35) Unary Post Expression
;  (35) Name Expression --
	iload_3
;  (35) End NameExpr
	iinc 3 1
;  (35) End UnaryPostExpr
	pop
;  (35) End ExprStat
	goto L6
L7:
;  (35) End ForStat
;  (37) Expression Statement
;  (37) Invocation
;  (37) Field Reference
;  (37) Name Expression --
;  (37) End NameExpr
	getstatic System/out LIo;
;  (37) End FieldRef
	pop
;  (37) Literal
	ldc ""
;  (37) End Literal
	invokestatic Io/println(Ljava/lang/String;)V
;  (37) End Invocation
;  (37) End ExprStat
L3:
;  (34) Expression Statement
;  (34) Unary Post Expression
;  (34) Name Expression --
	iload_2
;  (34) End NameExpr
	iinc 2 1
;  (34) End UnaryPostExpr
	pop
;  (34) End ExprStat
	goto L1
L2:
;  (34) End ForStat
;  (39) For Statement
;  (39) Local Variable Declaration
;  (39) Literal
	iconst_0
;  (39) End Literal
	istore 4
;  (39) End LocalDecl
L11:
;  (39) Binary Expression
;  (39) Name Expression --
	iload 4
;  (39) End NameExpr
;  (39) Array length
;  (39) Name Expression --
	aload_1
;  (39) End NameExpr
	arraylength
	if_icmplt L14
	iconst_0
	goto L15
L14:
	iconst_1
L15:
;  (39) End BinaryExpr
	ifeq L12
;  (40) For Statement
;  (40) Local Variable Declaration
;  (40) Literal
	iconst_0
;  (40) End Literal
	istore 5
;  (40) End LocalDecl
L16:
;  (40) Binary Expression
;  (40) Name Expression --
	iload 5
;  (40) End NameExpr
;  (40) Array length
;  (40) ArrayAccessExpr
;  (40) Name Expression --
	aload_1
;  (40) End NameExpr
;  (40) Name Expression --
	iload 4
;  (40) End NameExpr
	aaload
;  (40) End ArrayAccessExpr
	arraylength
	if_icmplt L19
	iconst_0
	goto L20
L19:
	iconst_1
L20:
;  (40) End BinaryExpr
	ifeq L17
;  (41) Expression Statement
;  (41) Invocation
;  (41) Field Reference
;  (41) Name Expression --
;  (41) End NameExpr
	getstatic System/out LIo;
;  (41) End FieldRef
	pop
;  (41) Binary Expression
	new java/lang/StringBuilder
	dup
	invokespecial java/lang/StringBuilder/<init>()V
;  (41) Invocation
;  (41) ArrayAccessExpr
;  (41) ArrayAccessExpr
;  (41) Name Expression --
	aload_1
;  (41) End NameExpr
;  (41) Name Expression --
	iload 4
;  (41) End NameExpr
	aaload
;  (41) End ArrayAccessExpr
;  (41) Name Expression --
	iload 5
;  (41) End NameExpr
	aaload
;  (41) End ArrayAccessExpr
	invokevirtual A/get()Ljava/lang/String;
;  (41) End Invocation
	invokevirtual java/lang/StringBuilder/append(Ljava/lang/String;)Ljava/lang/StringBuilder;
;  (41) Literal
	ldc " "
;  (41) End Literal
	invokevirtual java/lang/StringBuilder/append(Ljava/lang/String;)Ljava/lang/StringBuilder;
	invokevirtual java/lang/StringBuilder/toString()Ljava/lang/String;
;  (41) End BinaryExpr
	invokestatic Io/print(Ljava/lang/String;)V
;  (41) End Invocation
;  (41) End ExprStat
L18:
;  (40) Expression Statement
;  (40) Unary Post Expression
;  (40) Name Expression --
	iload 5
;  (40) End NameExpr
	iinc 5 1
;  (40) End UnaryPostExpr
	pop
;  (40) End ExprStat
	goto L16
L17:
;  (40) End ForStat
;  (42) Expression Statement
;  (42) Invocation
;  (42) Field Reference
;  (42) Name Expression --
;  (42) End NameExpr
	getstatic System/out LIo;
;  (42) End FieldRef
	pop
;  (42) Literal
	ldc ""
;  (42) End Literal
	invokestatic Io/println(Ljava/lang/String;)V
;  (42) End Invocation
;  (42) End ExprStat
L13:
;  (39) Expression Statement
;  (39) Unary Post Expression
;  (39) Name Expression --
	iload 4
;  (39) End NameExpr
	iinc 4 1
;  (39) End UnaryPostExpr
	pop
;  (39) End ExprStat
	goto L11
L12:
;  (39) End ForStat
	return
.end method

.method public <init>()V
	.limit stack 50
	.limit locals 1
;  (0) Constructor Declaration
;  (0) Explicit Constructor Invocation
	aload_0
	invokespecial java/lang/Object/<init>()V
;  (0) End CInvocation
;  (0) Field Init Generation Start
;  (0) Field Init Generation End
	return
.end method

